mkdocs_import_statement_plugin/__init__.py
mkdocs_import_statement_plugin/plugin.py
mkdocs_import_statement_plugin-23.1.4.dist-info/LICENSE
mkdocs_import_statement_plugin-23.1.4.dist-info/METADATA
mkdocs_import_statement_plugin-23.1.4.dist-info/WHEEL
mkdocs_import_statement_plugin-23.1.4.dist-info/entry_points.txt
mkdocs_import_statement_plugin-23.1.4.dist-info/top_level.txt
mkdocs_import_statement_plugin-23.1.4.dist-info/RECORD
