Metadata-Version: 2.1
Name: mkdocs-import-statement-plugin
Version: 23.1.4
Summary: MkDocs plugin to insert images and tables from files into markdown.
Home-page: https://github.com/Rj40x40/mkdocs-import-statement-plugin/
Author: Rj40x40
Author-email: Rj40x40dev@gmail.com
License: MIT
Requires-Python: >=3.6
License-File: LICENSE
Requires-Dist: mkdocs (>=1.4)
